prompt_refiner/__init__.py
prompt_refiner/pipeline.py
prompt_refiner/refiner.py
prompt_refiner/analyzer/__init__.py
prompt_refiner/analyzer/token_counters.py
prompt_refiner/analyzer/token_tracker.py
prompt_refiner/cleaner/__init__.py
prompt_refiner/cleaner/html.py
prompt_refiner/cleaner/json.py
prompt_refiner/cleaner/unicode.py
prompt_refiner/cleaner/whitespace.py
prompt_refiner/compressor/__init__.py
prompt_refiner/compressor/deduplicate.py
prompt_refiner/compressor/truncate.py
prompt_refiner/packer/__init__.py
prompt_refiner/packer/base.py
prompt_refiner/packer/messages.py
prompt_refiner/packer/text.py
prompt_refiner/scrubber/__init__.py
prompt_refiner/scrubber/pii.py
prompt_refiner/strategy/__init__.py
prompt_refiner/strategy/aggressive.py
prompt_refiner/strategy/minimal.py
prompt_refiner/strategy/standard.py
prompt_refiner/tools/__init__.py
prompt_refiner/tools/response_compressor.py
prompt_refiner/tools/schema_compressor.py
llm_prompt_refiner-0.2.3.dist-info/METADATA
llm_prompt_refiner-0.2.3.dist-info/WHEEL
llm_prompt_refiner-0.2.3.dist-info/licenses/LICENSE
llm_prompt_refiner-0.2.3.dist-info/RECORD
