Metadata-Version: 2.4
Name: llm-prompt-refiner
Version: 0.2.3
Summary: A lightweight Python library for optimizing and cleaning LLM inputs
Project-URL: Homepage, https://github.com/JacobHuang91/prompt-refiner
Project-URL: Repository, https://github.com/JacobHuang91/prompt-refiner
Project-URL: Issues, https://github.com/JacobHuang91/prompt-refiner/issues
Project-URL: Documentation, https://jacobhuang91.github.io/prompt-refiner/
Author-email: Xinghao Huang <jacobhuang91@gmail.com>
License: MIT
License-File: LICENSE
Keywords: agents,ai,chatbots,llm,optimization,prompt,rag,tokens
Classifier: Development Status :: 3 - Alpha
Classifier: Intended Audience :: Developers
Classifier: License :: OSI Approved :: MIT License
Classifier: Programming Language :: Python :: 3
Classifier: Programming Language :: Python :: 3.9
Classifier: Programming Language :: Python :: 3.10
Classifier: Programming Language :: Python :: 3.11
Classifier: Programming Language :: Python :: 3.12
Requires-Python: >=3.9
Provides-Extra: token
Requires-Dist: tiktoken>=0.7.0; extra == 'token'
